MANIFEST.in
README.rst
TITLE.txt
lh-agpl3-LICENSE.txt
setup.py
bin/pkgBearerTokenExampleManage.py
bin/roPerf-bearerTokenExample.sh
roPerf/__init__.py
roPerf.bearerTokenExample.egg-info/PKG-INFO
roPerf.bearerTokenExample.egg-info/SOURCES.txt
roPerf.bearerTokenExample.egg-info/dependency_links.txt
roPerf.bearerTokenExample.egg-info/namespace_packages.txt
roPerf.bearerTokenExample.egg-info/not-zip-safe
roPerf.bearerTokenExample.egg-info/requires.txt
roPerf.bearerTokenExample.egg-info/top_level.txt
roPerf/bearerTokenExample/__init__.py
roPerf/bearerTokenExample/bearerTokenExample_pkgThis.py
roPerf/bearerTokenExample-base/controllers/token_controller.py
roPerf/bearerTokenExample-base/controllers/token_controller.py.2to3
roPerf/bearerTokenExample-base/controllers/token_controller.py.3
roPerf/bearerTokenExample-base/controllers/token_controller.py.bak
roPerf/bearerTokenExample-base/svcSpec/bearerTokenExample.yaml
roPerf/bearerTokenExample-config/pkgInfo/fp/icmsPkgBasesPolicy/_tree_
roPerf/bearerTokenExample-config/pkgInfo/fp/icmsPkgBasesPolicy/value
roPerf/bearerTokenExample-config/pkgInfo/fp/icmsPkgControlBaseDir/_tree_
roPerf/bearerTokenExample-config/pkgInfo/fp/icmsPkgControlBaseDir/value
roPerf/bearerTokenExample-config/pkgInfo/fp/icmsPkgControlName/_tree_
roPerf/bearerTokenExample-config/pkgInfo/fp/icmsPkgControlName/value
roPerf/bearerTokenExample-config/pkgInfo/fp/icmsPkgLogBaseDir/_tree_
roPerf/bearerTokenExample-config/pkgInfo/fp/icmsPkgLogBaseDir/value
roPerf/bearerTokenExample-config/pkgInfo/fp/icmsPkgName/_tree_
roPerf/bearerTokenExample-config/pkgInfo/fp/icmsPkgName/value
roPerf/bearerTokenExample-config/pkgInfo/fp/icmsPkgTmpBaseDir/_tree_
roPerf/bearerTokenExample-config/pkgInfo/fp/icmsPkgTmpBaseDir/value
roPerf/bearerTokenExample-config/pkgInfo/fp/icmsPkgVarBaseDir/_tree_
roPerf/bearerTokenExample-config/pkgInfo/fp/icmsPkgVarBaseDir/value
roPerf/bearerTokenExample-config/svcInfo/portNu